[
    {
        "Artikelbeschreibung": "Designer Sofa Couch 3 Sitzer Polstermöbel Couchen Möbel Textil Stoff",
        "Currency": "7",
        "Startpreis": "2399",
        "Typ": "9",
        "Menge": "2",
        "SofortkaufenPreis": "0,0000",
        "CategoryID": "38208",
        "Category2ID": "0",
        "GalleryURL": "https://jvfurniture.eu/NEW_JOBS_2023/32_messoni/EINSTELLEN/BUBBLE/27/0_2-Sitzer.JPG",
        "Adult": "False",
        "BindingAuction": "False",
        "BoldTitle": "False",
        "CheckoutEnabled": "False",
        "Featured": "False",
        "Gallery": "True",
        "GalleryFeatured": "False",
        "Highlight": "False",
        "Private": "False",
        "ReserveLowered": "False",
        "ReserveMet": "False",
        "ReserveRemoved": "False",
        "SuperFeatured": "False",
        "Location": "Burgrieden",
        "Mindestgebot": "0,0000",
        "Pay_COD": "False",
        "Pay_Abholung": "False",
        "Pay_CCAccepted": "False",
        "Pay_Other": "False",
        "Pay_PayPalAccepted": "False",
        "Pay_SeeDescription": "False",
        "Pay_CashOnPickupAccepted": "False",
        "Pay_MoneyXferAccepted": "False",
        "Pay_MoneyXferAcceptedinCheckout": "False",
        "Pay_PersonalCheck": "False",
        "PhotoCount": "0",
        "PhotoDisplayType": "7",
        "PictureURL": "https://jvfurniture.eu/NEW_JOBS_2023/32_messoni/EINSTELLEN/BUBBLE/27/0_2-Sitzer.JPG",
        "Region": "0.0",
        "ShippingOption": "",
        "Ship_Afrika": "False",
        "Ship_Caribbean": "False",
        "Ship_Europe": "False",
        "Ship_LatinAmerica": "False",
        "Ship_NorthAmerica": "False",
        "Ship_SouthAmerica": "False",
        "Ship_BuyerPayBySellersFixed": "False",
        "Ship_BuyerPaysActual": "True",
        "Ship_SeeDescription": "False",
        "Ship_SellerPays": "False",
        "TitleBarImage": "False",
        "UUID": "",
        "ZIP": "88483",
        "Description": "<-StammBeschreibung->",
        "Ship_AdditionalShippingCosts": "0,0000",
        "Ship_AllowPaymentEdit": "False",
        "Ship_CheckoutInstructions": "",
        "Ship_InsuranceFee": "0,0000",
        "Ship_InsuranceOption": "0",
        "Ship_ShippingHandlingCosts": "0,0000",
        "Ship_ShippingRate": "0",
        "CheckoutDetailsSpecified": "0",
        "Counter": "0",
        "Dauer": "9999",
        "shopkat": "9956253013",
        "kollektion": "500132",
        "treuhand": "False",
        "SubtitleText": "",
        "I_stammartikel": "178559791",
        "SiteID": "77",
        "QuickCheckout": "False",
        "VorlageKopf": "0",
        "VorlageFuss": "0",
        "Country": "de",
        "VATPercent": "0",
        "ShipToLocations": "DE;",
        "NowAndNew": "False",
        "SecOffer": "False",
        "SecOfferPrice": "0,0000",
        "SecOfferDauer": "0",
        "SubAccount": "0",
        "LotSize": "0",
        "shopcat2": "0",
        "Reserve_Price": "0,0000",
        "ItemBorder": "False",
        "EBestOffer": "False",
        "StammPrice": "False",
        "PriceStc": "0",
        "eBayExpress": "False",
        "TransferCurr": "0",
        "GetItFast": "False",
        "WiderrufDauer": "0",
        "DispatchTimeMax": "0",
        "SupremeGallery": "0",
        "EBestOfferMinimum": "0,0000",
        "GalleryPlus": "False",
        "ShippingTermsInDescription": "False",
        "ProPackPlusBundle": "False",
        "Pay_ELV": "False",
        "MengenRedutkion": "False",
        "AuffuellMindestMenge": "0",
        "AuffuellMenge": "0",
        "AuffuelRest": "False",
        "ListAvailable": "0.0",
        "DiscountPriceType": "",
        "DiscountPriceAmount": "",
        "QuantityRelationshipType": "0.0",
        "PaymentProfileId": "0.0",
        "ReturnPolicyProfileId": "146898291013.0",
        "ShippingProfileId": "148681797013.0",
        "pictureurls": "https://jvfurniture.eu/NEW_JOBS_2023/32_messoni/EINSTELLEN/BUBBLE/27/detail%20%281%29.JPG;https://jvfurniture.eu/NEW_JOBS_2023/32_messoni/EINSTELLEN/BUBBLE/27/detail%20%282%29.JPG;https://jvfurniture.eu/NEW_JOBS_2023/32_messoni/EINSTELLEN/BUBBLE/27/detail%20%283%29.JPG;https://jvfurniture.eu/NEW_JOBS_2023/32_messoni/EINSTELLEN/BUBBLE/27/detail%20%284%29.JPG;https://jvfurniture.eu/NEW_JOBS_2023/32_messoni/EINSTELLEN/BUBBLE/27/detail%20%285%29.JPG;https://jvfurniture.eu/NEW_JOBS_2023/32_messoni/EINSTELLEN/BUBBLE/27/detail%20%286%29.JPG;https://jvfurniture.eu/NEW_JOBS_2023/32_messoni/EINSTELLEN/BUBBLE/27/detail%20%287%29.JPG;https://jvfurniture.eu/NEW_JOBS_2023/32_messoni/EINSTELLEN/BUBBLE/27/detail%20%288%29.JPG;https://jvfurniture.eu/NEW_JOBS_2023/32_messoni/EINSTELLEN/BUBBLE/27/detail%20%289%29.JPG;https://jvfurniture.eu/NEW_JOBS_2023/32_messoni/EINSTELLEN/BUBBLE/27/detail%20%2810%29.JPG;https://jvfurniture.eu/NEW_JOBS_2023/32_messoni/EINSTELLEN/BUBBLE/27/detail%20%2811%29.JPG",
        "MotorsGermanySearchable": "False",
        "sprachcode": "",
        "BusinessSeller": "False",
        "RestrictedToBusiness": "False",
        "GalleryDuration": "0",
        "VariationType": "0",
        "VarAvailabilityType": "0",
        "UseShippingDiscount": "False",
        "UseShippingDiscountInternational": "False",
        "NoExcludeShipping": "False",
        "UseProductField": "2.0",
        "IncludePrefilledInfo": "0.0",
        "PackstationVerbieten": "False",
        "ShippingDiscountProfileId": "0.0",
        "InternationalShippingDiscountProfileId": "0.0",
        "iPhoneBanner": "0.0",
        "PartsFitmentProductOption": "",
        "UseTopOffer": "",
        "UseDomesticShippingRateTable": "",
        "UseInternationalShippingRateTable": "",
        "PriceAdditionRuleId": "0.0",
        "EbayPlus": "False",
        "ConditionDescription": "",
        "useProductWeight": "False",
        "UseManufacturerInformation": "",
        "ManufacturerInformationLabel": "",
        "ConditionID": "1000.0",
        "DisableUseCrossGallery": "1.0",
        "CrossSellingGallery": "&RefillProducts=0",
        "EbayProductId": "",
        "Produktart": "Sofa",
        "Polsterstoff": "Polyester",
        "Marke": "JV Möbel",
        "Farbe": "Grau",
        "Breite": "97 cm",
        "Länge": "260 cm",
        "Höhe": "73 cm",
        "Anzahl der Teile": "2",
        "Füllmaterial": "Polyester",
        "Anzahl der Sitzplätze": "3",
        "Besonderheiten": "Mit Kissen",
        "Gestellmaterial": "Holz",
        "Muster": "Einfarbig",
        "Abteilung": [
            "Jugendliche",
            "Erwachsene"
        ],
        "Sitztiefe": "56 cm",
        "Montage erforderlich": "Ja",
        "Zusätzlich benötigte Teile": "Nein",
        "Herstellernummer": "JVM4067282432239",
        "Zimmer": [
            "Wohnzimmer",
            "Gästezimmer"
        ],
        "Stil": "Modern/Zeitgenössisch",
        "Härtegrad": "Mittelweich",
        "Sitzhöhe": "46 cm",
        "Herstellungsjahr": "Aktuell",
        "Angebotspaket": "Nein",
        "Herstellergarantie": "2 Jahre",
        "Verpackung": "Karton",
        "EAN": "4067282432239",
        "Maße Sofa 3 Sitzer": "ca: 260 x 97 x 73 cm",
        "Fabric": "Saloni_(TR)"
    },
    {
        "Artikelbeschreibung": "Weiß-Braune Esszimmer Garnitur Moderner Esstisch + 4x Stühle 5tlg Set",
        "Currency": "7",
        "Startpreis": "3749",
        "Typ": "9",
        "Menge": "2",
        "SofortkaufenPreis": "0,0000",
        "CategoryID": "107578",
        "Category2ID": "0",
        "GalleryURL": "http://varvara.de/NEWJOBS_3_GALYA/5_sanatmobilya.com_558x/EINSTELLEN/B_2022_saloni_sofa_catalog/148/Set%205%20tlg_tisch+4%20stuehle.JPG",
        "Adult": "False",
        "BindingAuction": "False",
        "BoldTitle": "False",
        "CheckoutEnabled": "False",
        "Featured": "False",
        "Gallery": "True",
        "GalleryFeatured": "False",
        "Highlight": "False",
        "Private": "False",
        "ReserveLowered": "False",
        "ReserveMet": "False",
        "ReserveRemoved": "False",
        "SuperFeatured": "False",
        "Location": "Burgrieden",
        "Mindestgebot": "0,0000",
        "Pay_COD": "False",
        "Pay_Abholung": "False",
        "Pay_CCAccepted": "False",
        "Pay_Other": "False",
        "Pay_PayPalAccepted": "False",
        "Pay_SeeDescription": "False",
        "Pay_CashOnPickupAccepted": "False",
        "Pay_MoneyXferAccepted": "False",
        "Pay_MoneyXferAcceptedinCheckout": "False",
        "Pay_PersonalCheck": "False",
        "PhotoCount": "0",
        "PhotoDisplayType": "7",
        "PictureURL": "http://varvara.de/NEWJOBS_3_GALYA/5_sanatmobilya.com_558x/EINSTELLEN/B_2022_saloni_sofa_catalog/148/Set%205%20tlg_tisch+4%20stuehle.JPG",
        "Region": "0.0",
        "ShippingOption": "",
        "Ship_Afrika": "False",
        "Ship_Caribbean": "False",
        "Ship_Europe": "False",
        "Ship_LatinAmerica": "False",
        "Ship_NorthAmerica": "False",
        "Ship_SouthAmerica": "False",
        "Ship_BuyerPayBySellersFixed": "False",
        "Ship_BuyerPaysActual": "True",
        "Ship_SeeDescription": "False",
        "Ship_SellerPays": "False",
        "TitleBarImage": "False",
        "UUID": "",
        "ZIP": "88483",
        "Description": "<-StammBeschreibung->",
        "Ship_AdditionalShippingCosts": "0,0000",
        "Ship_AllowPaymentEdit": "False",
        "Ship_CheckoutInstructions": "",
        "Ship_InsuranceFee": "0,0000",
        "Ship_InsuranceOption": "0",
        "Ship_ShippingHandlingCosts": "0,0000",
        "Ship_ShippingRate": "0",
        "CheckoutDetailsSpecified": "0",
        "Counter": "0",
        "Dauer": "9999",
        "shopkat": "9956310013",
        "kollektion": "500132",
        "treuhand": "False",
        "SubtitleText": "",
        "I_stammartikel": "177636794",
        "SiteID": "77",
        "QuickCheckout": "False",
        "VorlageKopf": "0",
        "VorlageFuss": "0",
        "Country": "de",
        "VATPercent": "0",
        "ShipToLocations": "DE;",
        "NowAndNew": "False",
        "SecOffer": "False",
        "SecOfferPrice": "0,0000",
        "SecOfferDauer": "0",
        "SubAccount": "0",
        "LotSize": "0",
        "shopcat2": "0",
        "Reserve_Price": "0,0000",
        "ItemBorder": "False",
        "EBestOffer": "False",
        "StammPrice": "False",
        "PriceStc": "0",
        "eBayExpress": "False",
        "TransferCurr": "0",
        "GetItFast": "False",
        "WiderrufDauer": "0",
        "DispatchTimeMax": "0",
        "SupremeGallery": "0",
        "EBestOfferMinimum": "0,0000",
        "GalleryPlus": "False",
        "ShippingTermsInDescription": "False",
        "ProPackPlusBundle": "False",
        "Pay_ELV": "False",
        "MengenRedutkion": "False",
        "AuffuellMindestMenge": "0",
        "AuffuellMenge": "0",
        "AuffuelRest": "False",
        "ListAvailable": "0.0",
        "DiscountPriceType": "",
        "DiscountPriceAmount": "",
        "QuantityRelationshipType": "0.0",
        "PaymentProfileId": "0.0",
        "ReturnPolicyProfileId": "146898291013.0",
        "ShippingProfileId": "148681797013.0",
        "pictureurls": "http://varvara.de/NEWJOBS_3_GALYA/5_sanatmobilya.com_558x/EINSTELLEN/B_2022_saloni_sofa_catalog/148/x1.JPG",
        "MotorsGermanySearchable": "False",
        "sprachcode": "",
        "BusinessSeller": "False",
        "RestrictedToBusiness": "False",
        "GalleryDuration": "0",
        "VariationType": "0",
        "VarAvailabilityType": "0",
        "UseShippingDiscount": "False",
        "UseShippingDiscountInternational": "False",
        "NoExcludeShipping": "False",
        "UseProductField": "2.0",
        "IncludePrefilledInfo": "0.0",
        "PackstationVerbieten": "False",
        "ShippingDiscountProfileId": "0.0",
        "InternationalShippingDiscountProfileId": "0.0",
        "iPhoneBanner": "0.0",
        "PartsFitmentProductOption": "",
        "UseTopOffer": "",
        "UseDomesticShippingRateTable": "",
        "UseInternationalShippingRateTable": "",
        "PriceAdditionRuleId": "0.0",
        "EbayPlus": "False",
        "ConditionDescription": "",
        "useProductWeight": "False",
        "UseManufacturerInformation": "",
        "ManufacturerInformationLabel": "",
        "ConditionID": "1000.0",
        "DisableUseCrossGallery": "1.0",
        "CrossSellingGallery": "&RefillProducts=0",
        "EbayProductId": "",
        "Anzahl der Teile": "5",
        "Marke": "JV Möbel",
        "Set enthält": [
            "Esstisch",
            "Stühle"
        ],
        "Anzahl der Sitzplätze": "4",
        "Zimmer": [
            "Esszimmer",
            "Küche"
        ],
        "Material": "Holzwerkstoff",
        "Farbe": "Braun",
        "Breite": "103 cm",
        "Montage erforderlich": "Ja",
        "Abteilung": [
            "Jungen",
            "Mädchen",
            "Jugendliche",
            "Erwachsene"
        ],
        "Länge": "219 cm",
        "Höhe": "76 cm",
        "Zusätzlich benötigte Teile": "Nein",
        "Form": "Rechteckig",
        "Stil": "Modern/Zeitgenössisch",
        "Montage": "Freistehend",
        "Angebotspaket": "Nein",
        "Herstellergarantie": "2 Jahre",
        "Verpackung": "Karton",
        "EAN": "4067282278424",
        "Herstellernummer": "JVM4067282278424",
        "Maße Esstisch": "ca: 219 x 103 x 76 cm",
        "Maße 4х Stühle": "ca: 51 x 47 x 85 cm",
        "Fabric": "Saloni_(TR)"
    },
    {
        "Artikelbeschreibung": "Sofa 3 Sitz Couch Polster Sofas Couchen Wohnzimmer Design Textil Stoff",
        "Currency": "7",
        "Startpreis": "2399",
        "Typ": "9",
        "Menge": "2",
        "SofortkaufenPreis": "0,0000",
        "CategoryID": "38208",
        "Category2ID": "0",
        "GalleryURL": "http://varvara.de/NEWJOBS_3_GALYA/5_sanatmobilya.com_558x/EINSTELLEN/B_2022_saloni_sofa_catalog/287/Sofa.JPG",
        "Adult": "False",
        "BindingAuction": "False",
        "BoldTitle": "False",
        "CheckoutEnabled": "False",
        "Featured": "False",
        "Gallery": "True",
        "GalleryFeatured": "False",
        "Highlight": "False",
        "Private": "False",
        "ReserveLowered": "False",
        "ReserveMet": "False",
        "ReserveRemoved": "False",
        "SuperFeatured": "False",
        "Location": "Burgrieden",
        "Mindestgebot": "0,0000",
        "Pay_COD": "False",
        "Pay_Abholung": "False",
        "Pay_CCAccepted": "False",
        "Pay_Other": "False",
        "Pay_PayPalAccepted": "False",
        "Pay_SeeDescription": "False",
        "Pay_CashOnPickupAccepted": "False",
        "Pay_MoneyXferAccepted": "False",
        "Pay_MoneyXferAcceptedinCheckout": "False",
        "Pay_PersonalCheck": "False",
        "PhotoCount": "0",
        "PhotoDisplayType": "7",
        "PictureURL": "http://varvara.de/NEWJOBS_3_GALYA/5_sanatmobilya.com_558x/EINSTELLEN/B_2022_saloni_sofa_catalog/287/Sofa.JPG",
        "Region": "0.0",
        "ShippingOption": "",
        "Ship_Afrika": "False",
        "Ship_Caribbean": "False",
        "Ship_Europe": "False",
        "Ship_LatinAmerica": "False",
        "Ship_NorthAmerica": "False",
        "Ship_SouthAmerica": "False",
        "Ship_BuyerPayBySellersFixed": "False",
        "Ship_BuyerPaysActual": "True",
        "Ship_SeeDescription": "False",
        "Ship_SellerPays": "False",
        "TitleBarImage": "False",
        "UUID": "",
        "ZIP": "88483",
        "Description": "<-StammBeschreibung->",
        "Ship_AdditionalShippingCosts": "0,0000",
        "Ship_AllowPaymentEdit": "False",
        "Ship_CheckoutInstructions": "",
        "Ship_InsuranceFee": "0,0000",
        "Ship_InsuranceOption": "0",
        "Ship_ShippingHandlingCosts": "0,0000",
        "Ship_ShippingRate": "0",
        "CheckoutDetailsSpecified": "0",
        "Counter": "0",
        "Dauer": "9999",
        "shopkat": "9956253013",
        "kollektion": "500132",
        "treuhand": "False",
        "SubtitleText": "",
        "I_stammartikel": "177454381",
        "SiteID": "77",
        "QuickCheckout": "False",
        "VorlageKopf": "0",
        "VorlageFuss": "0",
        "Country": "de",
        "VATPercent": "0",
        "ShipToLocations": "DE;",
        "NowAndNew": "False",
        "SecOffer": "False",
        "SecOfferPrice": "0,0000",
        "SecOfferDauer": "0",
        "SubAccount": "0",
        "LotSize": "0",
        "shopcat2": "0",
        "Reserve_Price": "0,0000",
        "ItemBorder": "False",
        "EBestOffer": "False",
        "StammPrice": "False",
        "PriceStc": "0",
        "eBayExpress": "False",
        "TransferCurr": "0",
        "GetItFast": "False",
        "WiderrufDauer": "0",
        "DispatchTimeMax": "0",
        "SupremeGallery": "0",
        "EBestOfferMinimum": "0,0000",
        "GalleryPlus": "False",
        "ShippingTermsInDescription": "False",
        "ProPackPlusBundle": "False",
        "Pay_ELV": "False",
        "MengenRedutkion": "False",
        "AuffuellMindestMenge": "0",
        "AuffuellMenge": "0",
        "AuffuelRest": "False",
        "ListAvailable": "0.0",
        "DiscountPriceType": "",
        "DiscountPriceAmount": "",
        "QuantityRelationshipType": "0.0",
        "PaymentProfileId": "0.0",
        "ReturnPolicyProfileId": "146898291013.0",
        "ShippingProfileId": "148681797013.0",
        "pictureurls": "http://varvara.de/NEWJOBS_3_GALYA/5_sanatmobilya.com_558x/EINSTELLEN/B_2022_saloni_sofa_catalog/287/x1.JPG;http://varvara.de/NEWJOBS_3_GALYA/5_sanatmobilya.com_558x/EINSTELLEN/B_2022_saloni_sofa_catalog/287/x2.JPG",
        "MotorsGermanySearchable": "False",
        "sprachcode": "",
        "BusinessSeller": "False",
        "RestrictedToBusiness": "False",
        "GalleryDuration": "0",
        "VariationType": "0",
        "VarAvailabilityType": "0",
        "UseShippingDiscount": "False",
        "UseShippingDiscountInternational": "False",
        "NoExcludeShipping": "False",
        "UseProductField": "2.0",
        "IncludePrefilledInfo": "0.0",
        "PackstationVerbieten": "False",
        "ShippingDiscountProfileId": "0.0",
        "InternationalShippingDiscountProfileId": "0.0",
        "iPhoneBanner": "0.0",
        "PartsFitmentProductOption": "",
        "UseTopOffer": "",
        "UseDomesticShippingRateTable": "",
        "UseInternationalShippingRateTable": "",
        "PriceAdditionRuleId": "0.0",
        "EbayPlus": "False",
        "ConditionDescription": "",
        "useProductWeight": "False",
        "UseManufacturerInformation": "",
        "ManufacturerInformationLabel": "",
        "ConditionID": "1000.0",
        "DisableUseCrossGallery": "1.0",
        "CrossSellingGallery": "&RefillProducts=0",
        "EbayProductId": "",
        "Produktart": "Sofa",
        "Polsterstoff": "Polyester",
        "Marke": "JV Möbel",
        "Farbe": "Beige",
        "Breite": "ca: 89 cm",
        "Länge": "ca: 216 cm",
        "Höhe": "ca: 75 cm",
        "Anzahl der Teile": "1",
        "Anzahl der Sitzplätze": "3",
        "Gestellmaterial": "Holz",
        "Abteilung": [
            "Jungen",
            "Mädchen",
            "Jugendliche",
            "Erwachsene"
        ],
        "Sitztiefe": "ca: 58 cm",
        "Montage erforderlich": "Ja",
        "Zusätzlich benötigte Teile": "Nein",
        "Zimmer": "Wohnzimmer",
        "Stil": "Modern/Zeitgenössisch",
        "Sitzhöhe": "ca: 41 cm",
        "Herstellungsjahr": "Aktuell",
        "Angebotspaket": "Nein",
        "Herstellergarantie": "2 Jahre",
        "Montage": "Freistehend",
        "Verpackung": "Karton",
        "EAN": "4067282277540",
        "Herstellernummer": "JVM4067282277540",
        "Maße Sofa 3 Sitzer": "ca: 216 x 89 x 75 cm",
        "Fabric": "Saloni_(TR)"
    }
]